qflip/__init__.py
qflip/qflip.py
qflip_CQPANCOAST-1.0.2.dist-info/LICENSE
qflip_CQPANCOAST-1.0.2.dist-info/METADATA
qflip_CQPANCOAST-1.0.2.dist-info/WHEEL
qflip_CQPANCOAST-1.0.2.dist-info/entry_points.txt
qflip_CQPANCOAST-1.0.2.dist-info/top_level.txt
qflip_CQPANCOAST-1.0.2.dist-info/RECORD
