Metadata-Version: 2.1
Name: qflip-CQPANCOAST
Version: 1.0.2
Summary: Determinism is for losers - make your decisions using quantum mechanics.
Home-page: https://github.com/cqpancoast/quantum-flip
Author: Casey Pancoast
License: MIT
Keywords: quantum coin flip rng qrng qflip flip universe
Platform: UNKNOWN
Classifier: Programming Language :: Python
Classifier: License :: OSI Approved :: MIT License
Classifier: Operating System :: OS Independent
Classifier: Topic :: Scientific/Engineering :: Physics
